parameterfree/__init__.py
parameterfree/cocob.py
parameterfree/kt.py
parameterfree-0.0.1.dist-info/LICENSE
parameterfree-0.0.1.dist-info/METADATA
parameterfree-0.0.1.dist-info/WHEEL
parameterfree-0.0.1.dist-info/top_level.txt
parameterfree-0.0.1.dist-info/RECORD
