Metadata-Version: 2.1
Name: parameterfree
Version: 0.0.1
Summary: Parameter-Free Optimizers for Pytorch
Home-page: https://github.com/bremen79/parameterfree
Author: Francesco Orabona
Author-email: francesco@orabona.com
License: UNKNOWN
Platform: UNKNOWN
Classifier: License :: OSI Approved :: MIT License
Classifier: Programming Language :: Python :: 3
Classifier: Operating System :: OS Independent
Requires-Python: >=3.6
License-File: LICENSE
